README.md
setup.py
extras/pyneapple.desktop
pyneapple/__init__.py
pyneapple/__main__.py
pyneapple/config.py
pyneapple/platform.py
pyneapple.egg-info/PKG-INFO
pyneapple.egg-info/SOURCES.txt
pyneapple.egg-info/dependency_links.txt
pyneapple.egg-info/requires.txt
pyneapple.egg-info/top_level.txt
pyneapple/custom/custom.css
pyneapple/custom/custom.js
pyneapple/custom/theme-borlandia.css
pyneapple/custom/theme-dark.css
pyneapple/custom/theme-light.css
pyneapple/custom/theme-red.css
pyneapple/custom/fonts/Apache License.txt
pyneapple/custom/fonts/GreatVibes-Regular.otf
pyneapple/custom/fonts/LessPerfectDOSVGA.ttf
pyneapple/custom/fonts/MorePerfectDOSVGA.ttf
pyneapple/custom/fonts/Roboto-Bold-webfont.ttf
pyneapple/custom/fonts/Roboto-BoldItalic-webfont.ttf
pyneapple/custom/fonts/Roboto-Italic-webfont.ttf
pyneapple/custom/fonts/Roboto-Light-webfont.ttf
pyneapple/custom/fonts/Roboto-LightItalic-webfont.ttf
pyneapple/custom/fonts/Roboto-Medium-webfont.ttf
pyneapple/custom/fonts/Roboto-MediumItalic-webfont.ttf
pyneapple/custom/fonts/Roboto-Regular-webfont.ttf
pyneapple/custom/fonts/Roboto-Thin-webfont.ttf
pyneapple/custom/fonts/Roboto-ThinItalic-webfont.ttf
pyneapple/custom/fonts/RobotoSlab-Bold-webfont.ttf
pyneapple/custom/fonts/RobotoSlab-Regular-webfont.ttf
pyneapple/custom/images/blue-mocha-grunge-reversed.jpg
pyneapple/custom/images/borlandia-tile.png
pyneapple/custom/images/cream-dust.png
pyneapple/custom/images/cream-dust2.png
pyneapple/custom/images/stripe.png
pyneapple/custom/images/stripe2.png
pyneapple/custom/nbextensions/button.js
pyneapple/custom/nbextensions/readonly.js
pyneapple/custom/nbextensions/tabs.js
pyneapple/custom/nbextensions/theme.js
pyneapple/data/defaults.cfg
pyneapple/data/menu.ui
pyneapple/data/pyneapple-old.ui~
pyneapple/data/pyneapple.ui
pyneapple/data/windows.ui
pyneapple/data/windows.ui~
scripts/pyneapple