Metadata-Version: 1.0
Name: pyneapple
Version: 0.3
Summary: GTK Editor for Jupyter Notebooks
Home-page: http://github.com/darthoctopus/pyneapple
Author: Joel Ong
Author-email: joel.ong@yale.edu
License: GPLv3
Keywords: jupyter notebook GTK
Platform: UNKNOWN
